csvnav.py
csvnav-0.1.0.dist-info/LICENSE.txt
csvnav-0.1.0.dist-info/METADATA
csvnav-0.1.0.dist-info/WHEEL
csvnav-0.1.0.dist-info/top_level.txt
csvnav-0.1.0.dist-info/RECORD
