Metadata-Version: 2.1
Name: csvnav
Version: 0.1.0
Summary: A python 3 class for memory-efficient navigation of CSV/Text files.
Home-page: https://github.com/jkaardal/csvnav
Author: Joel Kaardal
Author-email: jkaardal@gmail.com
License: MIT
Download-URL: https://pypi.org/project/csvnav/
Keywords: data-science,csv,machine-learning,data-analysis,memory-management
Platform: UNKNOWN
